wizardspell/__init__.py
wizardspell/wizard_spell.py
wizardspell/THIRD_PARTY_LICENSES/THIRD-PARTY-DICTIONARIES.md
wizardspell/THIRD_PARTY_LICENSES/apache-2.0.txt
wizardspell/wizard_analyze_text/__init__.py
wizardspell/wizard_analyze_text/wizard_correctness/__init__.py
wizardspell/wizard_analyze_text/wizard_correctness/_unicode_tokenizer.py
wizardspell/wizard_analyze_text/wizard_correctness/_utils.py
wizardspell/wizard_analyze_text/wizard_correctness/correctness.py
wizardspell/wizard_analyze_text/wizard_correctness/loader_dict.py
wizardspell-1.0.0.dist-info/licenses/LICENSE
wizardspell-1.0.0.dist-info/METADATA
wizardspell-1.0.0.dist-info/WHEEL
wizardspell-1.0.0.dist-info/top_level.txt
wizardspell-1.0.0.dist-info/RECORD
