Metadata-Version: 2.4
Name: wizardspell
Version: 1.0.0
Summary: Dictionary-based spell checking with Unicode-aware tokenization and light normalization. Supports 62 languages via compressed Marisa-Trie dictionaries and returns a compact report of misspellings.
Author-email: Mattia Rubino <textwizard.dev@gmail.com>
License: WizardSpell — Copyright (C) 2024–2025 Mattia Rubino
Project-URL: Homepage, https://github.com/textwizard-dev/wizardspell
Project-URL: Source, https://github.com/textwizard-dev/wizardspell
Project-URL: Documentation, https://wizardspell.readthedocs.io/en/latest/
Keywords: spell-check,spell-checking,spelling,dictionary,marisa-trie,nlp,text-processing,unicode,tokenization,multilingual,iso-639,mmap,zstd,python-library
Classifier: Programming Language :: Python :: 3
Classifier: Programming Language :: Python :: 3.9
Classifier: Programming Language :: Python :: 3.10
Classifier: Programming Language :: Python :: 3.11
Classifier: Intended Audience :: Developers
Classifier: Topic :: Text Processing
Classifier: License :: OSI Approved :: GNU Affero General Public License v3 or later (AGPLv3+)
Requires-Python: >=3.9
License-File: LICENSE
Requires-Dist: marisa-trie>=1.3.0
Requires-Dist: zstandard>=0.22
Requires-Dist: platformdirs>=4.0
Requires-Dist: regex>=2024.11.6
Dynamic: license-file
